README.rst
setup.py
eprl/__init__.py
eprl/cli.py
eprl/colors.py
eprl/dbstore.py
eprl/dbutil.py
eprl/eprl.py
eprl/resolver.py
eprl/restore.py
eprl/util.py
eprl/vargs.py
eprl.egg-info/PKG-INFO
eprl.egg-info/SOURCES.txt
eprl.egg-info/dependency_links.txt
eprl.egg-info/entry_points.txt
eprl.egg-info/top_level.txt