Metadata-Version: 1.1
Name: eprl
Version: 1.1
Summary: edit portage resume list
Home-page: https://github.com/borysn/eprl
Author: borysn
Author-email: xborysn@gmail.com
License: MIT
Keywords: python3 script gentoo linux edit portage resume list
Platform: UNKNOWN
Classifier: Environment :: Console
Classifier: Intended Audience :: End Users/Desktop
Classifier: Intended Audience :: Developers
Classifier: Intended Audience :: System Administrators
Classifier: License :: OSI Approved :: MIT License
Classifier: Operating System :: POSIX :: Linux
Classifier: Programming Language :: Python :: 3
Classifier: Topic :: Database
Classifier: Topic :: System :: Software Distribution
Classifier: Topic :: System :: Systems Administration
Classifier: Topic :: Utilities
